maco/model/__init__.py
maco/model/model.py
maco_model-1.2.20.dist-info/licenses/LICENSE.md
maco_model-1.2.20.dist-info/METADATA
maco_model-1.2.20.dist-info/WHEEL
maco_model-1.2.20.dist-info/top_level.txt
maco_model-1.2.20.dist-info/RECORD
